{
  "parent": "minecraft:husbandry/root",
  "display": {
    "icon": {
      "item": "cornharvest:corncob"
    },
    "title": {
      "translate": "cornharvest.advancements.husbandry.plant_corn.title"
    },
    "description": {
      "translate": "cornharvest.advancements.husbandry.plant_corn.description"
    },
    "frame": "task",
    "show_toast": true,
    "announce_to_chat": true,
    "hidden": false
  },
  "criteria": {
    "corn": {
      "trigger": "minecraft:placed_block",
      "conditions": {
        "block": "cornharvest:corn"
      }
    }
  },
  "requirements": [
    [
      "corn"
    ]
  ]
}